larql/__init__.py
larql/parser.py
larql/sparql.lark
larql/utils/validators.py
larql-0.1.0.dist-info/METADATA
larql-0.1.0.dist-info/WHEEL
larql-0.1.0.dist-info/entry_points.txt
larql-0.1.0.dist-info/RECORD
