Metadata-Version: 2.4
Name: larql
Version: 0.1.0
Summary: Lark Parser for SPARQL 1.1
Author-email: Lukas Plank <lupl@tuta.io>
Requires-Python: >=3.11
Requires-Dist: lark>=1.2.2
